sjt/__init__.py
sjt/__main__.py
sjt/config.py
sjt/sjt.py
sjt/utils.py
tests/__init__.py
tests/test_utils.py
sjt-0.1.2.dist-info/LICENSE
sjt-0.1.2.dist-info/METADATA
sjt-0.1.2.dist-info/WHEEL
sjt-0.1.2.dist-info/entry_points.txt
sjt-0.1.2.dist-info/top_level.txt
sjt-0.1.2.dist-info/RECORD
